rlviser_py-0.6.13.dist-info/METADATA
rlviser_py-0.6.13.dist-info/WHEEL
rlviser_py-0.6.13.dist-info/licenses/LICENSE
rlviser_py/__init__.py
rlviser_py/__init__.pyi
rlviser_py/py.typed
rlviser_py/rlviser_py.pyd
rlviser_py-0.6.13.dist-info/RECORD
