Metadata-Version: 2.4
Name: rlviser-py
Version: 0.6.13
Classifier: Programming Language :: Rust
Classifier: Programming Language :: Python :: Implementation :: CPython
Classifier: Programming Language :: Python :: Implementation :: PyPy
License-File: LICENSE
Summary: Python implementation that manages a UDP connection to RLViser
Requires-Python: >=3.7
Project-URL: Source Code, https://github.com/VirxEC/rlviser-py
